Metadata-Version: 2.1
Name: l3gd20-python
Version: 1.0.0
Summary: Python library for the L3GD20 I2C 3-axis gyroscope
Home-page: https://github.com/jackw01/l3gd20-python
Author: jackw01
License: MIT
Platform: UNKNOWN
Classifier: License :: OSI Approved :: MIT License
Classifier: Programming Language :: Python
Classifier: Programming Language :: Python :: 3
Classifier: Programming Language :: Python :: Implementation :: CPython
Classifier: Programming Language :: Python :: Implementation :: PyPy
Requires-Python: >=3.7.0
